eqt_ext/__init__.py
eqt_ext/eqt.py
eqt_ext/_static/css/eqt.css
eqt_ext/_static/js/eqt.js
sphinx_ext_eqt-1.4.data/data/_static/eqt.css
sphinx_ext_eqt-1.4.data/data/_static/eqt.js
sphinx_ext_eqt-1.4.dist-info/METADATA
sphinx_ext_eqt-1.4.dist-info/RECORD
sphinx_ext_eqt-1.4.dist-info/WHEEL
sphinx_ext_eqt-1.4.dist-info/top_level.txt
